conmato/__init__.py
conmato/check_plagiarism.py
conmato/cli.py
conmato/contest.py
conmato/crawl_standings.py
conmato/csession.py
conmato/member.py
conmato/mossum.py
conmato/parameters.py
conmato/utils.py
conmato-0.0.5.dist-info/LICENSE
conmato-0.0.5.dist-info/METADATA
conmato-0.0.5.dist-info/WHEEL
conmato-0.0.5.dist-info/entry_points.txt
conmato-0.0.5.dist-info/top_level.txt
conmato-0.0.5.dist-info/RECORD
