Metadata-Version: 2.1
Name: conmato
Version: 0.0.5
Summary: A Command Line Interface for Codeforces Management Tools
Author: Ngoc Bui
Author-email: ngocjr7@gmail.com
Project-URL: Bug Tracker, https://github.com/ngocjr7/codeforces-management-tools/issues
Project-URL: Documentation, https://github.com/ngocjr7/codeforces-management-tools/blob/master/README.md
Project-URL: Source Code, https://github.com/ngocjr7/codeforces-management-tools
Requires-Python: >=3.6
License-File: LICENSE
Requires-Dist: html5lib
Requires-Dist: beautifulsoup4
Requires-Dist: certifi
Requires-Dist: chardet
Requires-Dist: cssselect
Requires-Dist: idna
Requires-Dist: lxml
Requires-Dist: mosspy
Requires-Dist: numpy
Requires-Dist: pandas
Requires-Dist: pydot
Requires-Dist: pyparsing
Requires-Dist: pyquery
Requires-Dist: python-dateutil
Requires-Dist: pytz
Requires-Dist: requests
Requires-Dist: six
Requires-Dist: soupsieve
Requires-Dist: urllib3
Requires-Dist: openpyxl
Requires-Dist: jinja2 (>=2.11.3)
Requires-Dist: xlrd
Requires-Dist: click
Requires-Dist: pyyaml
Requires-Dist: tqdm
Requires-Dist: appdirs
Requires-Dist: scoss
